{
  "傀影與猩紅孤鑽": [
    "指揮分隊",
    "集群分隊",
    "後勤分隊",
    "矛頭分隊",
    "突擊戰術分隊",
    "堡壘戰術分隊",
    "遠程戰術分隊",
    "破壞戰術分隊",
    "研究分隊",
    "高規格分隊"
  ],
  "水月與深藍之樹": [
    "心勝於物分隊",
    "物盡其用分隊",
    "以人為本分隊",
    "指揮分隊",
    "集群分隊",
    "後勤分隊",
    "矛頭分隊",
    "突擊戰術分隊",
    "堡壘戰術分隊",
    "遠程戰術分隊",
    "破壞戰術分隊",
    "研究分隊",
    "高規格分隊"
  ],
  "探索者的銀凇止境": [
    "永恆狩獵分隊",
    "生活至上分隊",
    "科學主義分隊",
    "特訓分隊",
    "指揮分隊",
    "集群分隊",
    "後勤分隊",
    "矛頭分隊",
    "突擊戰術分隊",
    "堡壘戰術分隊",
    "遠程戰術分隊",
    "破壞戰術分隊",
    "高規格分隊"
  ],
  "薩卡茲的無終奇語": [
    "魂靈護送分隊",
    "博聞廣記分隊",
    "藍圖測繪分隊",
    "因地制宜分隊",
    "指揮分隊",
    "集群分隊",
    "後勤分隊",
    "矛頭分隊",
    "突擊戰術分隊",
    "堡壘戰術分隊",
    "遠程戰術分隊",
    "破壞戰術分隊",
    "高規格分隊",
    "點刺成錠分隊",
    "擬態學者分隊",
    "異想天開分隊",
    "專業人士分隊"
  ],
  "歲的界園誌異": [
    "指揮分隊",
    "特勤分隊",
    "後勤分隊",
    "突擊戰術分隊",
    "堡壘戰術分隊",
    "遠程戰術分隊",
    "破壞戰術分隊",
    "高台突破分隊",
    "地面突破分隊",
    "高規格分隊",
    "遊客分隊",
    "司歲台分隊",
    "天師府分隊",
    "花團錦簇分隊",
    "棋行險著分隊",
    "歲影回音分隊",
    "代理人分隊",
    "知學分隊",
    "商賈分隊"
  ]
}